LICENSE
MANIFEST.in
README.rst
setup.py
lib/qprompt.py
qprompt.egg-info/PKG-INFO
qprompt.egg-info/SOURCES.txt
qprompt.egg-info/dependency_links.txt
qprompt.egg-info/requires.txt
qprompt.egg-info/top_level.txt
tests/_Run_Tests.py
tests/ask_test_1.py
tests/cast_test_1.py
tests/menu_helper_1.py
tests/menu_test_1.py
tests/menu_test_2.py
tests/menu_test_3.py
tests/menu_test_4.py
tests/menu_test_5.py
tests/menu_test_6.py
tests/menu_test_7.py
tests/menu_test_8.py
tests/menu_test_9.py
tests/status_test_1.py
tests/testlib.py
tests/testlib.pyc
tests/__pycache__/testlib.cpython-35.pyc
tests/__pycache__/testlib.cpython-36.pyc
tests/__pycache__/testlib.cpython-37.pyc