Metadata-Version: 1.1
Name: qprompt
Version: 0.15.5
Summary: Library for quick CLI user prompts, input, and menus.
Home-page: https://github.com/jeffrimko/Qprompt
Author: Jeff Rimko
Author-email: jeffrimko@gmail.com
License: MIT
Keywords: cli menu prompt input user library
Platform: UNKNOWN
Classifier: Development Status :: 4 - Beta
Classifier: Topic :: Utilities
Classifier: Programming Language :: Python :: 2.7
Classifier: Programming Language :: Python :: 3
Classifier: License :: OSI Approved :: MIT License
Classifier: Operating System :: OS Independent
